staticdash/__init__.py
staticdash/dashboard.py
staticdash/assets/css/style.css
staticdash/assets/js/script.js
staticdash/assets/vendor/mathjax/tex-mml-chtml.js
staticdash/assets/vendor/plotly/plotly.min.js
staticdash/assets/vendor/prism/prism-tomorrow.min.css
staticdash/assets/vendor/prism/prism.min.js
staticdash/assets/vendor/prism/components/prism-bash.min.js
staticdash/assets/vendor/prism/components/prism-c.min.js
staticdash/assets/vendor/prism/components/prism-javascript.min.js
staticdash/assets/vendor/prism/components/prism-json.min.js
staticdash/assets/vendor/prism/components/prism-markup.min.js
staticdash/assets/vendor/prism/components/prism-python.min.js
staticdash/assets/vendor/prism/components/prism-sql.min.js
staticdash-2026.6.dist-info/METADATA
staticdash-2026.6.dist-info/WHEEL
staticdash-2026.6.dist-info/top_level.txt
staticdash-2026.6.dist-info/RECORD
