Metadata-Version: 2.4
Name: staticdash
Version: 2026.6
Summary: A lightweight static HTML dashboard generator with Plotly and pandas support.
Author-email: Brian Day <brian.day1@gmail.com>
License: CC0-1.0
Project-URL: Homepage, https://github.com/staticdash/staticdash
Project-URL: Repository, https://github.com/staticdash/staticdash
Requires-Python: >=3.8
Requires-Dist: plotly
Requires-Dist: pandas
Requires-Dist: dominate
Requires-Dist: matplotlib
Provides-Extra: images
Requires-Dist: kaleido; extra == "images"
Provides-Extra: all
Requires-Dist: kaleido; extra == "all"
